[
    {
        "k": "class7",
        "v": "Study Hall",
        "schedule": "(Monday, R2 1:50-2:35)"
    },
    {
        "k": "class26",
        "v": "Small Eats & Sweet Treats",
        "schedule": "(Thursday, R1 1:05-1:50)"
    },
    {
        "k": "class10",
        "v": "Badminton Basics",
        "schedule": "(Wednesday, R1 1:05-1:50 and R2 1:50-2:35)"
    },
    {
        "k": "class11",
        "v": "Yearbook Class",
        "schedule": "(Monday, R1 1:05-1:50)"
    },
    {
        "k": "class27",
        "v": "Anatomy Lab",
        "schedule": "(Monday, R1 1:05-1:50)"
    },
    {
        "k": "class6",
        "v": "Nail Art",
        "schedule": "(Thursday, R1 1:05-1:50)"
    },
    {
        "k": "class16",
        "v": "Dungeons & Dragons",
        "schedule": "(Friday, R1 1:05-1:50 and R2 1:50-2:35)"
    },
    {
        "k": "class1",
        "v": "Uke can do it!",
        "schedule": "(Monday, R1 1:05-1:50 and R2 1:50-2:35)"
    },
    {
        "k": "class20",
        "v": "Learn Russian",
        "schedule": "(Friday, R1 1:05-1:50)"
    },
    {
        "k": "class21",
        "v": "Go Find Your Spark...",
        "schedule": "(Thursday, R2 1:50-2:35)"
    },
    {
        "k": "class17",
        "v": "The GSA: Gender and Sexualities Alliance",
        "schedule": "(Monday, R2 1:50-2:35)"
    },
    {
        "k": "class14",
        "v": "Flag Football and Kickball",
        "schedule": "(Friday, R1 1:05-1:50 and R2 1:50-2:35)"
    },
    {
        "k": "class18",
        "v": "Student Newsletter: Planning",
        "schedule": "(Wednesday, R1 1:05-1:50)"
    },
    {
        "k": "class22",
        "v": "Art as Mindfulness",
        "schedule": "(Wednesday, R2 1:50-2:35)"
    },
    {
        "k": "class3",
        "v": "Game and Grub",
        "schedule": "(Friday, R2 1:50-2:35)"
    },
    {
        "k": "class2",
        "v": "Slime Boss: Your Guide to Running a Business",
        "schedule": "(Thursday, R1 1:05-1:50 and R2 1:50-2:35)"
    },
    {
        "k": "class23",
        "v": "Studio Art",
        "schedule": "(Thursday, both rotations 1:05-2:35)"
    },
    {
        "k": "class19",
        "v": "Student Newsletter: Writing",
        "schedule": "(Wednesday, R2 1:50-2:35)"
    },
    {
        "k": "class15",
        "v": "Creative Sign Art!",
        "schedule": "(Monday, R1 1:05-1:50 and R2 1:50-2:35)"
    },
    {
        "k": "class24",
        "v": "2D Art",
        "schedule": "(Friday, R2 1:50-2:35)"
    },
    {
        "k": "class5",
        "v": "Contest Math",
        "schedule": "(Monday, R2 1:50-2:35)"
    },
    {
        "k": "class12",
        "v": "Family Game Night",
        "schedule": "(Wednesday, R1 1:05-1:50)"
    },
    {
        "k": "class9",
        "v": "Visual Storytelling: Comic Strip Memoirs",
        "schedule": "(Monday, R1 1:05-1:50)"
    },
    {
        "k": "class8",
        "v": "Bibliomaniacs",
        "schedule": "(Friday, R1 1:05-1:50 and R2 1:50-2:35)"
    },
    {
        "k": "class13",
        "v": "Volleyball",
        "schedule": "(Monday, R2 1:50-2:35)"
    },
    {
        "k": "class4",
        "v": "Microscope Lab",
        "schedule": "(Wednesday, R1 1:05-1:50)"
    },
    {
        "k": "class25",
        "v": "Impress Everyone with these Easy Dinner Recipes!",
        "schedule": "(Wednesday, R1 1:05-1:50)"
    }
]